{
  "dataList": [
    {
      "id": 1,
      "name": "อี้ซัง"
    },
    {
      "id": 2,
      "name": "เฟาสต์"
    },
    {
      "id": 3,
      "name": "ดอน กิโฆเต้"
    },
    {
      "id": 4,
      "name": "เรียวชู"
    },
    {
      "id": 5,
      "name": "เมอร์โซลท์"
    },
    {
      "id": 6,
      "name": "หงลู่"
    },
    {
      "id": 7,
      "name": "ฮีธคลิฟฟ์"
    },
    {
      "id": 8,
      "name": "อิชมาเอล"
    },
    {
      "id": 9,
      "name": "โรดิอน"
    },
    {
      "id": 10,
      "name": "ซินแคลร์"
    },
    {
      "id": 11,
      "name": "โอทิส"
    },
    {
      "id": 12,
      "name": "เกรเกอร์"
    }
  ]
}